streamsql/__init__.py
streamsql/client.py
streamsql/connect.py
streamsql/const.py
streamsql/execution.py
streamsql/matrix.py
streamsql/matrix_pb2.py
streamsql/matrix_pb2_grpc.py
streamsql-1.0.6.dist-info/LICENSE
streamsql-1.0.6.dist-info/METADATA
streamsql-1.0.6.dist-info/WHEEL
streamsql-1.0.6.dist-info/top_level.txt
streamsql-1.0.6.dist-info/RECORD
