Metadata-Version: 2.1
Name: streamsql
Version: 1.0.6
Summary: API package for StreamSQL
Home-page: https://streamsql.io
Author: streamsql
Author-email: help@streamsql.io
License: UNKNOWN
Platform: UNKNOWN
Classifier: Programming Language :: Python :: 3
Classifier: License :: OSI Approved :: MIT License
Classifier: Operating System :: OS Independent
Requires-Python: >=3.0
Requires-Dist: requests
